{
    "Total Columns": 170,
    "Column Names": [
        "username",
        "age",
        "gender",
        "industry",
        "profession",
        "phq9_total_score",
        "phq9_doctors_notes",
        "phq9_patients_notes",
        "dsm5_severity",
        "dsm5_q9_flag",
        "dsm5_mdd_assessment",
        "dsm5_created_at",
        "phq9_q0",
        "phq9_q1",
        "phq9_q2",
        "phq9_q3",
        "phq9_q4",
        "phq9_q5",
        "phq9_q6",
        "phq9_q7",
        "phq9_q8",
        "industry_enc",
        "profession_enc",
        "dsm5_severity_enc",
        "dsm5_q9_flag_enc",
        "dsm5_mdd_assessment_enc",
        "sim_date",
        "gender_enc",
        "age_bucket",
        "age_bucket_enc",
        "patients_sentiment",
        "doctors_sentiment",
        "patient_feeling tired",
        "patient_feeling restless",
        "patient_problems with daily routine",
        "patient_confused",
        "patient_trouble concentrating",
        "patient_frequent irritability",
        "patient_slight fatigue",
        "patient_difficulty focusing at work",
        "patient_okay",
        "patient_mood swings are noticeable",
        "patient_loss of interest in eating or personal care",
        "patient_persistent fatigue",
        "patient_low energy during the day",
        "patient_occasional low mood",
        "patient_low motivation",
        "patient_severe anxiety attacks",
        "patient_extreme lack of energy",
        "patient_fearful",
        "patient_finding it hard to maintain social connections",
        "patient_energy levels fluctuate during the day",
        "patient_feeling overwhelmed most of the day",
        "patient_appetite is irregular",
        "patient_gloomy",
        "patient_generally fine",
        "patient_down",
        "patient_frustrated",
        "patient_unmotivated",
        "patient_minor changes in sleep patterns",
        "patient_feeling lonely",
        "patient_lonely",
        "patient_disheartened",
        "patient_trapped",
        "patient_struggling to concentrate at work",
        "patient_restless",
        "patient_difficulty managing daily chores",
        "patient_persistent sadness",
        "patient_uneasy",
        "patient_sad",
        "patient_irritable",
        "patient_disconnected",
        "patient_overwhelmed",
        "patient_mild worry",
        "patient_sleep disturbances",
        "patient_sleep has been affected",
        "patient_desperate",
        "patient_manageable",
        "patient_occasional sadness",
        "patient_feeling a bit down in the evenings",
        "patient_a bit tired",
        "patient_significant drop in motivation",
        "patient_hopeless",
        "patient_loss of interest in hobbies",
        "patient_difficulty functioning",
        "patient_sometimes feeling distracted",
        "patient_completely drained",
        "patient_motivation is extremely low",
        "patient_thoughts of self-harm",
        "patient_persistent guilt and self-criticism",
        "patient_worthless",
        "patient_minor irritability",
        "patient_inability to get out of bed",
        "patient_discouraged",
        "patient_exhausted",
        "patient_helpless",
        "patient_distraught",
        "patient_bored",
        "patient_frequent negative thoughts",
        "patient_hopelessness",
        "patient_intense fear of future",
        "patient_social withdrawal",
        "patient_anxious",
        "patient_difficulty enjoying usual activities",
        "patient_slightly low",
        "doctor_evaluation",
        "doctor_Moderate",
        "doctor_visit",
        "doctor_behavioral",
        "doctor_safety",
        "doctor_monitoring",
        "doctor_review",
        "doctor_Severe",
        "doctor_Mild",
        "doctor_progress",
        "doctor_maintaining",
        "doctor_structured",
        "doctor_risk",
        "doctor_mindfulness",
        "doctor_possible",
        "doctor_care",
        "doctor_medication",
        "doctor_planning",
        "doctor_urgent",
        "doctor_intervention",
        "doctor_recommended",
        "doctor_active",
        "doctor_symptoms",
        "doctor_advised",
        "doctor_specialist",
        "doctor_immediate",
        "doctor_referral",
        "doctor_routines",
        "doctor_healthy",
        "doctor_factors",
        "doctor_guided",
        "doctor_next",
        "doctor_exercises",
        "doctor_combination",
        "doctor_selfhelp",
        "doctor_escalates",
        "doctor_psychiatric",
        "doctor_needed",
        "doctor_required",
        "doctor_and",
        "doctor_consider",
        "doctor_cognitive",
        "doctor_inpatient",
        "doctor_encourage",
        "doctor_continue",
        "doctor_suggest",
        "doctor_lowintensity",
        "doctor_therapy",
        "doctor_monitor",
        "doctor_selfcare",
        "doctor_None-minimal",
        "doctor_mental",
        "doctor_recommend",
        "doctor_health",
        "doctor_closely",
        "doctor_Moderately Severe",
        "doctor_cbt",
        "patient_suicide_score",
        "doctor_suicide_score",
        "patient_anxiety_score",
        "doctor_anxiety_score",
        "patient_symptom_score",
        "doctor_symptom_score",
        "consultation_seq",
        "days_since_last"
    ],
    "Columns": {
        "username": {
            "DataType": "object",
            "Non-Null Count": 4456,
            "Null Count": 0,
            "Unique Values": 163,
            "Mean": null,
            "Median": null,
            "Std": null,
            "Min": null,
            "Max": null,
            "Top": "Avni.3222",
            "Freq": 64
        },
        "age": {
            "DataType": "int64",
            "Non-Null Count": 4456,
            "Null Count": 0,
            "Unique Values": 47,
            "Mean": 41.931104129263915,
            "Median": 42.0,
            "Std": 14.70617458880851,
            "Min": 18.0,
            "Max": 65.0,
            "Top": null,
            "Freq": null
        },
        "gender": {
            "DataType": "object",
            "Non-Null Count": 4456,
            "Null Count": 0,
            "Unique Values": 2,
            "Mean": null,
            "Median": null,
            "Std": null,
            "Min": null,
            "Max": null,
            "Top": "Female",
            "Freq": 2501
        },
        "industry": {
            "DataType": "object",
            "Non-Null Count": 4456,
            "Null Count": 0,
            "Unique Values": 14,
            "Mean": null,
            "Median": null,
            "Std": null,
            "Min": null,
            "Max": null,
            "Top": "Retail",
            "Freq": 515
        },
        "profession": {
            "DataType": "object",
            "Non-Null Count": 4456,
            "Null Count": 0,
            "Unique Values": 92,
            "Mean": null,
            "Median": null,
            "Std": null,
            "Min": null,
            "Max": null,
            "Top": "Other",
            "Freq": 711
        },
        "phq9_total_score": {
            "DataType": "int64",
            "Non-Null Count": 4456,
            "Null Count": 0,
            "Unique Values": 28,
            "Mean": 10.175493716337522,
            "Median": 9.0,
            "Std": 5.747605052670798,
            "Min": 0.0,
            "Max": 27.0,
            "Top": null,
            "Freq": null
        },
        "phq9_doctors_notes": {
            "DataType": "object",
            "Non-Null Count": 4456,
            "Null Count": 0,
            "Unique Values": 192,
            "Mean": null,
            "Median": null,
            "Std": null,
            "Min": null,
            "Max": null,
            "Top": "This is the patient\u2019s 1 consultation. Assessment shows Mild depression. Recommend mindfulness exercises and monitoring symptoms.",
            "Freq": 83
        },
        "phq9_patients_notes": {
            "DataType": "object",
            "Non-Null Count": 4456,
            "Null Count": 0,
            "Unique Values": 770,
            "Mean": null,
            "Median": null,
            "Std": null,
            "Min": null,
            "Max": null,
            "Top": "During this 1 visit, I noticed that occasional low mood. It makes me feel generally fine and affects my daily life.",
            "Freq": 15
        },
        "dsm5_severity": {
            "DataType": "object",
            "Non-Null Count": 4456,
            "Null Count": 0,
            "Unique Values": 5,
            "Mean": null,
            "Median": null,
            "Std": null,
            "Min": null,
            "Max": null,
            "Top": "Mild depression",
            "Freq": 1578
        },
        "dsm5_q9_flag": {
            "DataType": "bool",
            "Non-Null Count": 4456,
            "Null Count": 0,
            "Unique Values": 2,
            "Mean": 0.34672351885098746,
            "Median": 0.0,
            "Std": 0.47598021334517915,
            "Min": 0.0,
            "Max": 1.0,
            "Top": null,
            "Freq": null
        },
        "dsm5_mdd_assessment": {
            "DataType": "bool",
            "Non-Null Count": 4456,
            "Null Count": 0,
            "Unique Values": 2,
            "Mean": 0.2318222621184919,
            "Median": 0.0,
            "Std": 0.4220434505190907,
            "Min": 0.0,
            "Max": 1.0,
            "Top": null,
            "Freq": null
        },
        "dsm5_created_at": {
            "DataType": "datetime64[ns, UTC]",
            "Non-Null Count": 4456,
            "Null Count": 0,
            "Unique Values": 800,
            "Mean": null,
            "Median": null,
            "Std": null,
            "Min": null,
            "Max": null,
            "Top": null,
            "Freq": null
        },
        "phq9_q0": {
            "DataType": "int64",
            "Non-Null Count": 4456,
            "Null Count": 0,
            "Unique Values": 4,
            "Mean": 1.1173698384201076,
            "Median": 1.0,
            "Std": 1.0654892043367161,
            "Min": 0.0,
            "Max": 3.0,
            "Top": null,
            "Freq": null
        },
        "phq9_q1": {
            "DataType": "int64",
            "Non-Null Count": 4456,
            "Null Count": 0,
            "Unique Values": 4,
            "Mean": 1.0902154398563735,
            "Median": 1.0,
            "Std": 1.0871903257041828,
            "Min": 0.0,
            "Max": 3.0,
            "Top": null,
            "Freq": null
        },
        "phq9_q2": {
            "DataType": "int64",
            "Non-Null Count": 4456,
            "Null Count": 0,
            "Unique Values": 4,
            "Mean": 1.0897666068222622,
            "Median": 1.0,
            "Std": 1.0451204944274606,
            "Min": 0.0,
            "Max": 3.0,
            "Top": null,
            "Freq": null
        },
        "phq9_q3": {
            "DataType": "int64",
            "Non-Null Count": 4456,
            "Null Count": 0,
            "Unique Values": 4,
            "Mean": 1.1609066427289048,
            "Median": 1.0,
            "Std": 1.0652800264328657,
            "Min": 0.0,
            "Max": 3.0,
            "Top": null,
            "Freq": null
        },
        "phq9_q4": {
            "DataType": "int64",
            "Non-Null Count": 4456,
            "Null Count": 0,
            "Unique Values": 4,
            "Mean": 1.119165170556553,
            "Median": 1.0,
            "Std": 1.0745210918139148,
            "Min": 0.0,
            "Max": 3.0,
            "Top": null,
            "Freq": null
        },
        "phq9_q5": {
            "DataType": "int64",
            "Non-Null Count": 4456,
            "Null Count": 0,
            "Unique Values": 4,
            "Mean": 1.1938958707360863,
            "Median": 1.0,
            "Std": 1.082093200332193,
            "Min": 0.0,
            "Max": 3.0,
            "Top": null,
            "Freq": null
        },
        "phq9_q6": {
            "DataType": "int64",
            "Non-Null Count": 4456,
            "Null Count": 0,
            "Unique Values": 4,
            "Mean": 1.0991921005385996,
            "Median": 1.0,
            "Std": 1.0262718524120131,
            "Min": 0.0,
            "Max": 3.0,
            "Top": null,
            "Freq": null
        },
        "phq9_q7": {
            "DataType": "int64",
            "Non-Null Count": 4456,
            "Null Count": 0,
            "Unique Values": 4,
            "Mean": 1.1411579892280073,
            "Median": 1.0,
            "Std": 1.0453479462808646,
            "Min": 0.0,
            "Max": 3.0,
            "Top": null,
            "Freq": null
        },
        "phq9_q8": {
            "DataType": "int64",
            "Non-Null Count": 4456,
            "Null Count": 0,
            "Unique Values": 4,
            "Mean": 1.1638240574506284,
            "Median": 1.0,
            "Std": 1.0487990500454394,
            "Min": 0.0,
            "Max": 3.0,
            "Top": null,
            "Freq": null
        },
        "industry_enc": {
            "DataType": "int64",
            "Non-Null Count": 4456,
            "Null Count": 0,
            "Unique Values": 14,
            "Mean": 6.980700179533214,
            "Median": 7.0,
            "Std": 3.9076413734314848,
            "Min": 0.0,
            "Max": 13.0,
            "Top": null,
            "Freq": null
        },
        "profession_enc": {
            "DataType": "int64",
            "Non-Null Count": 4456,
            "Null Count": 0,
            "Unique Values": 92,
            "Mean": 46.619389587073606,
            "Median": 51.0,
            "Std": 24.204731358632888,
            "Min": 0.0,
            "Max": 91.0,
            "Top": null,
            "Freq": null
        },
        "dsm5_severity_enc": {
            "DataType": "int64",
            "Non-Null Count": 4456,
            "Null Count": 0,
            "Unique Values": 5,
            "Mean": 1.3413375224416517,
            "Median": 1.0,
            "Std": 1.302835173801135,
            "Min": 0.0,
            "Max": 4.0,
            "Top": null,
            "Freq": null
        },
        "dsm5_q9_flag_enc": {
            "DataType": "int64",
            "Non-Null Count": 4456,
            "Null Count": 0,
            "Unique Values": 2,
            "Mean": 0.34672351885098746,
            "Median": 0.0,
            "Std": 0.47598021334517915,
            "Min": 0.0,
            "Max": 1.0,
            "Top": null,
            "Freq": null
        },
        "dsm5_mdd_assessment_enc": {
            "DataType": "int64",
            "Non-Null Count": 4456,
            "Null Count": 0,
            "Unique Values": 2,
            "Mean": 0.2318222621184919,
            "Median": 0.0,
            "Std": 0.4220434505190907,
            "Min": 0.0,
            "Max": 1.0,
            "Top": null,
            "Freq": null
        },
        "sim_date": {
            "DataType": "datetime64[ns, UTC]",
            "Non-Null Count": 4456,
            "Null Count": 0,
            "Unique Values": 365,
            "Mean": null,
            "Median": null,
            "Std": null,
            "Min": null,
            "Max": null,
            "Top": null,
            "Freq": null
        },
        "gender_enc": {
            "DataType": "int64",
            "Non-Null Count": 4456,
            "Null Count": 0,
            "Unique Values": 2,
            "Mean": 0.4387342908438061,
            "Median": 0.0,
            "Std": 0.49628800818757207,
            "Min": 0.0,
            "Max": 1.0,
            "Top": null,
            "Freq": null
        },
        "age_bucket": {
            "DataType": "category",
            "Non-Null Count": 4456,
            "Null Count": 0,
            "Unique Values": 5,
            "Mean": null,
            "Median": null,
            "Std": null,
            "Min": null,
            "Max": null,
            "Top": "56-65",
            "Freq": 1245
        },
        "age_bucket_enc": {
            "DataType": "int64",
            "Non-Null Count": 4456,
            "Null Count": 0,
            "Unique Values": 5,
            "Mean": 2.1624775583482942,
            "Median": 2.0,
            "Std": 1.4780372102917172,
            "Min": 0.0,
            "Max": 4.0,
            "Top": null,
            "Freq": null
        },
        "patients_sentiment": {
            "DataType": "float64",
            "Non-Null Count": 4456,
            "Null Count": 0,
            "Unique Values": 206,
            "Mean": -0.11049356049271893,
            "Median": -0.10500000000000001,
            "Std": 0.13577776215760673,
            "Min": -0.6,
            "Max": 0.27777777777777773,
            "Top": null,
            "Freq": null
        },
        "doctors_sentiment": {
            "DataType": "float64",
            "Non-Null Count": 4456,
            "Null Count": 0,
            "Unique Values": 5,
            "Mean": 0.1582024236983842,
            "Median": 0.06666666666666667,
            "Std": 0.18476142172700388,
            "Min": -0.05,
            "Max": 0.5,
            "Top": null,
            "Freq": null
        },
        "patient_feeling tired": {
            "DataType": "int64",
            "Non-Null Count": 4456,
            "Null Count": 0,
            "Unique Values": 2,
            "Mean": 0.051840215439856376,
            "Median": 0.0,
            "Std": 0.22172920574632546,
            "Min": 0.0,
            "Max": 1.0,
            "Top": null,
            "Freq": null
        },
        "patient_feeling restless": {
            "DataType": "int64",
            "Non-Null Count": 4456,
            "Null Count": 0,
            "Unique Values": 2,
            "Mean": 0.04959605026929982,
            "Median": 0.0,
            "Std": 0.21713328303528243,
            "Min": 0.0,
            "Max": 1.0,
            "Top": null,
            "Freq": null
        },
        "patient_problems with daily routine": {
            "DataType": "int64",
            "Non-Null Count": 4456,
            "Null Count": 0,
            "Unique Values": 2,
            "Mean": 0.018626570915619388,
            "Median": 0.0,
            "Std": 0.13521732485674665,
            "Min": 0.0,
            "Max": 1.0,
            "Top": null,
            "Freq": null
        },
        "patient_confused": {
            "DataType": "int64",
            "Non-Null Count": 4456,
            "Null Count": 0,
            "Unique Values": 2,
            "Mean": 0.044658886894075406,
            "Median": 0.0,
            "Std": 0.20657697712126816,
            "Min": 0.0,
            "Max": 1.0,
            "Top": null,
            "Freq": null
        },
        "patient_trouble concentrating": {
            "DataType": "int64",
            "Non-Null Count": 4456,
            "Null Count": 0,
            "Unique Values": 2,
            "Mean": 0.05632854578096948,
            "Median": 0.0,
            "Std": 0.2305809454239169,
            "Min": 0.0,
            "Max": 1.0,
            "Top": null,
            "Freq": null
        },
        "patient_frequent irritability": {
            "DataType": "int64",
            "Non-Null Count": 4456,
            "Null Count": 0,
            "Unique Values": 2,
            "Mean": 0.03096947935368043,
            "Median": 0.0,
            "Std": 0.17325445748048066,
            "Min": 0.0,
            "Max": 1.0,
            "Top": null,
            "Freq": null
        },
        "patient_slight fatigue": {
            "DataType": "int64",
            "Non-Null Count": 4456,
            "Null Count": 0,
            "Unique Values": 2,
            "Mean": 0.022666068222621186,
            "Median": 0.0,
            "Std": 0.1488532500008176,
            "Min": 0.0,
            "Max": 1.0,
            "Top": null,
            "Freq": null
        },
        "patient_difficulty focusing at work": {
            "DataType": "int64",
            "Non-Null Count": 4456,
            "Null Count": 0,
            "Unique Values": 2,
            "Mean": 0.0466786355475763,
            "Median": 0.0,
            "Std": 0.21097329036967236,
            "Min": 0.0,
            "Max": 1.0,
            "Top": null,
            "Freq": null
        },
        "patient_okay": {
            "DataType": "int64",
            "Non-Null Count": 4456,
            "Null Count": 0,
            "Unique Values": 2,
            "Mean": 0.03433572710951526,
            "Median": 0.0,
            "Std": 0.18211048172418473,
            "Min": 0.0,
            "Max": 1.0,
            "Top": null,
            "Freq": null
        },
        "patient_mood swings are noticeable": {
            "DataType": "int64",
            "Non-Null Count": 4456,
            "Null Count": 0,
            "Unique Values": 2,
            "Mean": 0.1099640933572711,
            "Median": 0.0,
            "Std": 0.31288010571311836,
            "Min": 0.0,
            "Max": 1.0,
            "Top": null,
            "Freq": null
        },
        "patient_loss of interest in eating or personal care": {
            "DataType": "int64",
            "Non-Null Count": 4456,
            "Null Count": 0,
            "Unique Values": 2,
            "Mean": 0.012118491921005385,
            "Median": 0.0,
            "Std": 0.10942724208371707,
            "Min": 0.0,
            "Max": 1.0,
            "Top": null,
            "Freq": null
        },
        "patient_persistent fatigue": {
            "DataType": "int64",
            "Non-Null Count": 4456,
            "Null Count": 0,
            "Unique Values": 2,
            "Mean": 0.03411131059245961,
            "Median": 0.0,
            "Std": 0.18153546418383745,
            "Min": 0.0,
            "Max": 1.0,
            "Top": null,
            "Freq": null
        },
        "patient_low energy during the day": {
            "DataType": "int64",
            "Non-Null Count": 4456,
            "Null Count": 0,
            "Unique Values": 2,
            "Mean": 0.045556552962298026,
            "Median": 0.0,
            "Std": 0.20854475184916052,
            "Min": 0.0,
            "Max": 1.0,
            "Top": null,
            "Freq": null
        },
        "patient_occasional low mood": {
            "DataType": "int64",
            "Non-Null Count": 4456,
            "Null Count": 0,
            "Unique Values": 2,
            "Mean": 0.02872531418312388,
            "Median": 0.0,
            "Std": 0.16705218697383395,
            "Min": 0.0,
            "Max": 1.0,
            "Top": null,
            "Freq": null
        },
        "patient_low motivation": {
            "DataType": "int64",
            "Non-Null Count": 4456,
            "Null Count": 0,
            "Unique Values": 2,
            "Mean": 0.03164272890484739,
            "Median": 0.0,
            "Std": 0.17506668617144716,
            "Min": 0.0,
            "Max": 1.0,
            "Top": null,
            "Freq": null
        },
        "patient_severe anxiety attacks": {
            "DataType": "int64",
            "Non-Null Count": 4456,
            "Null Count": 0,
            "Unique Values": 2,
            "Mean": 0.009425493716337522,
            "Median": 0.0,
            "Std": 0.09663720584841747,
            "Min": 0.0,
            "Max": 1.0,
            "Top": null,
            "Freq": null
        },
        "patient_extreme lack of energy": {
            "DataType": "int64",
            "Non-Null Count": 4456,
            "Null Count": 0,
            "Unique Values": 2,
            "Mean": 0.00807899461400359,
            "Median": 0.0,
            "Std": 0.08952945479475699,
            "Min": 0.0,
            "Max": 1.0,
            "Top": null,
            "Freq": null
        },
        "patient_fearful": {
            "DataType": "int64",
            "Non-Null Count": 4456,
            "Null Count": 0,
            "Unique Values": 2,
            "Mean": 0.00763016157989228,
            "Median": 0.0,
            "Std": 0.08702667329322471,
            "Min": 0.0,
            "Max": 1.0,
            "Top": null,
            "Freq": null
        },
        "patient_finding it hard to maintain social connections": {
            "DataType": "int64",
            "Non-Null Count": 4456,
            "Null Count": 0,
            "Unique Values": 2,
            "Mean": 0.07989228007181329,
            "Median": 0.0,
            "Std": 0.27115678878924426,
            "Min": 0.0,
            "Max": 1.0,
            "Top": null,
            "Freq": null
        },
        "patient_energy levels fluctuate during the day": {
            "DataType": "int64",
            "Non-Null Count": 4456,
            "Null Count": 0,
            "Unique Values": 2,
            "Mean": 0.10233393177737882,
            "Median": 0.0,
            "Std": 0.30312096280885503,
            "Min": 0.0,
            "Max": 1.0,
            "Top": null,
            "Freq": null
        },
        "patient_feeling overwhelmed most of the day": {
            "DataType": "int64",
            "Non-Null Count": 4456,
            "Null Count": 0,
            "Unique Values": 2,
            "Mean": 0.017953321364452424,
            "Median": 0.0,
            "Std": 0.13279667613351095,
            "Min": 0.0,
            "Max": 1.0,
            "Top": null,
            "Freq": null
        },
        "patient_appetite is irregular": {
            "DataType": "int64",
            "Non-Null Count": 4456,
            "Null Count": 0,
            "Unique Values": 2,
            "Mean": 0.08595152603231598,
            "Median": 0.0,
            "Std": 0.280323912984091,
            "Min": 0.0,
            "Max": 1.0,
            "Top": null,
            "Freq": null
        },
        "patient_gloomy": {
            "DataType": "int64",
            "Non-Null Count": 4456,
            "Null Count": 0,
            "Unique Values": 2,
            "Mean": 0.04780071813285458,
            "Median": 0.0,
            "Std": 0.21336828787589104,
            "Min": 0.0,
            "Max": 1.0,
            "Top": null,
            "Freq": null
        },
        "patient_generally fine": {
            "DataType": "int64",
            "Non-Null Count": 4456,
            "Null Count": 0,
            "Unique Values": 2,
            "Mean": 0.02625673249551167,
            "Median": 0.0,
            "Std": 0.15991577630183612,
            "Min": 0.0,
            "Max": 1.0,
            "Top": null,
            "Freq": null
        },
        "patient_down": {
            "DataType": "int64",
            "Non-Null Count": 4456,
            "Null Count": 0,
            "Unique Values": 2,
            "Mean": 0.06889587073608618,
            "Median": 0.0,
            "Std": 0.2533054067914247,
            "Min": 0.0,
            "Max": 1.0,
            "Top": null,
            "Freq": null
        },
        "patient_frustrated": {
            "DataType": "int64",
            "Non-Null Count": 4456,
            "Null Count": 0,
            "Unique Values": 2,
            "Mean": 0.04308797127468582,
            "Median": 0.0,
            "Std": 0.20307794831011367,
            "Min": 0.0,
            "Max": 1.0,
            "Top": null,
            "Freq": null
        },
        "patient_unmotivated": {
            "DataType": "int64",
            "Non-Null Count": 4456,
            "Null Count": 0,
            "Unique Values": 2,
            "Mean": 0.07136445242369839,
            "Median": 0.0,
            "Std": 0.257461537179165,
            "Min": 0.0,
            "Max": 1.0,
            "Top": null,
            "Freq": null
        },
        "patient_minor changes in sleep patterns": {
            "DataType": "int64",
            "Non-Null Count": 4456,
            "Null Count": 0,
            "Unique Values": 2,
            "Mean": 0.02199281867145422,
            "Median": 0.0,
            "Std": 0.14667638762566051,
            "Min": 0.0,
            "Max": 1.0,
            "Top": null,
            "Freq": null
        },
        "patient_feeling lonely": {
            "DataType": "int64",
            "Non-Null Count": 4456,
            "Null Count": 0,
            "Unique Values": 2,
            "Mean": 0.030296229802513466,
            "Median": 0.0,
            "Std": 0.1714204268261434,
            "Min": 0.0,
            "Max": 1.0,
            "Top": null,
            "Freq": null
        },
        "patient_lonely": {
            "DataType": "int64",
            "Non-Null Count": 4456,
            "Null Count": 0,
            "Unique Values": 2,
            "Mean": 0.053635547576301616,
            "Median": 0.0,
            "Std": 0.2253223674583848,
            "Min": 0.0,
            "Max": 1.0,
            "Top": null,
            "Freq": null
        },
        "patient_disheartened": {
            "DataType": "int64",
            "Non-Null Count": 4456,
            "Null Count": 0,
            "Unique Values": 2,
            "Mean": 0.02064631956912029,
            "Median": 0.0,
            "Std": 0.14221317726891738,
            "Min": 0.0,
            "Max": 1.0,
            "Top": null,
            "Freq": null
        },
        "patient_trapped": {
            "DataType": "int64",
            "Non-Null Count": 4456,
            "Null Count": 0,
            "Unique Values": 2,
            "Mean": 0.017055655296229804,
            "Median": 0.0,
            "Std": 0.1294933320761557,
            "Min": 0.0,
            "Max": 1.0,
            "Top": null,
            "Freq": null
        },
        "patient_struggling to concentrate at work": {
            "DataType": "int64",
            "Non-Null Count": 4456,
            "Null Count": 0,
            "Unique Values": 2,
            "Mean": 0.11377917414721724,
            "Median": 0.0,
            "Std": 0.3175785059697098,
            "Min": 0.0,
            "Max": 1.0,
            "Top": null,
            "Freq": null
        },
        "patient_restless": {
            "DataType": "int64",
            "Non-Null Count": 4456,
            "Null Count": 0,
            "Unique Values": 2,
            "Mean": 0.08258527827648116,
            "Median": 0.0,
            "Std": 0.2752852281022005,
            "Min": 0.0,
            "Max": 1.0,
            "Top": null,
            "Freq": null
        },
        "patient_difficulty managing daily chores": {
            "DataType": "int64",
            "Non-Null Count": 4456,
            "Null Count": 0,
            "Unique Values": 2,
            "Mean": 0.09851885098743267,
            "Median": 0.0,
            "Std": 0.2980483560434169,
            "Min": 0.0,
            "Max": 1.0,
            "Top": null,
            "Freq": null
        },
        "patient_persistent sadness": {
            "DataType": "int64",
            "Non-Null Count": 4456,
            "Null Count": 0,
            "Unique Values": 2,
            "Mean": 0.023114901256732497,
            "Median": 0.0,
            "Std": 0.15028529932860626,
            "Min": 0.0,
            "Max": 1.0,
            "Top": null,
            "Freq": null
        },
        "patient_uneasy": {
            "DataType": "int64",
            "Non-Null Count": 4456,
            "Null Count": 0,
            "Unique Values": 2,
            "Mean": 0.06373429084380611,
            "Median": 0.0,
            "Std": 0.2443064171376308,
            "Min": 0.0,
            "Max": 1.0,
            "Top": null,
            "Freq": null
        },
        "patient_sad": {
            "DataType": "int64",
            "Non-Null Count": 4456,
            "Null Count": 0,
            "Unique Values": 2,
            "Mean": 0.10233393177737882,
            "Median": 0.0,
            "Std": 0.30312096280885503,
            "Min": 0.0,
            "Max": 1.0,
            "Top": null,
            "Freq": null
        },
        "patient_irritable": {
            "DataType": "int64",
            "Non-Null Count": 4456,
            "Null Count": 0,
            "Unique Values": 2,
            "Mean": 0.044658886894075406,
            "Median": 0.0,
            "Std": 0.20657697712126816,
            "Min": 0.0,
            "Max": 1.0,
            "Top": null,
            "Freq": null
        },
        "patient_disconnected": {
            "DataType": "int64",
            "Non-Null Count": 4456,
            "Null Count": 0,
            "Unique Values": 2,
            "Mean": 0.03141831238779174,
            "Median": 0.0,
            "Std": 0.174464990275439,
            "Min": 0.0,
            "Max": 1.0,
            "Top": null,
            "Freq": null
        },
        "patient_overwhelmed": {
            "DataType": "int64",
            "Non-Null Count": 4456,
            "Null Count": 0,
            "Unique Values": 2,
            "Mean": 0.078770197486535,
            "Median": 0.0,
            "Std": 0.26940998870905364,
            "Min": 0.0,
            "Max": 1.0,
            "Top": null,
            "Freq": null
        },
        "patient_mild worry": {
            "DataType": "int64",
            "Non-Null Count": 4456,
            "Null Count": 0,
            "Unique Values": 2,
            "Mean": 0.03164272890484739,
            "Median": 0.0,
            "Std": 0.17506668617144716,
            "Min": 0.0,
            "Max": 1.0,
            "Top": null,
            "Freq": null
        },
        "patient_sleep disturbances": {
            "DataType": "int64",
            "Non-Null Count": 4456,
            "Null Count": 0,
            "Unique Values": 2,
            "Mean": 0.02423698384201077,
            "Median": 0.0,
            "Std": 0.15380136864725694,
            "Min": 0.0,
            "Max": 1.0,
            "Top": null,
            "Freq": null
        },
        "patient_sleep has been affected": {
            "DataType": "int64",
            "Non-Null Count": 4456,
            "Null Count": 0,
            "Unique Values": 2,
            "Mean": 0.07585278276481149,
            "Median": 0.0,
            "Std": 0.26479213176990146,
            "Min": 0.0,
            "Max": 1.0,
            "Top": null,
            "Freq": null
        },
        "patient_desperate": {
            "DataType": "int64",
            "Non-Null Count": 4456,
            "Null Count": 0,
            "Unique Values": 2,
            "Mean": 0.00718132854578097,
            "Median": 0.0,
            "Std": 0.08444736502995037,
            "Min": 0.0,
            "Max": 1.0,
            "Top": null,
            "Freq": null
        },
        "patient_manageable": {
            "DataType": "int64",
            "Non-Null Count": 4456,
            "Null Count": 0,
            "Unique Values": 2,
            "Mean": 0.03298922800718133,
            "Median": 0.0,
            "Std": 0.17862838393502245,
            "Min": 0.0,
            "Max": 1.0,
            "Top": null,
            "Freq": null
        },
        "patient_occasional sadness": {
            "DataType": "int64",
            "Non-Null Count": 4456,
            "Null Count": 0,
            "Unique Values": 2,
            "Mean": 0.04622980251346499,
            "Median": 0.0,
            "Std": 0.21000596468586846,
            "Min": 0.0,
            "Max": 1.0,
            "Top": null,
            "Freq": null
        },
        "patient_feeling a bit down in the evenings": {
            "DataType": "int64",
            "Non-Null Count": 4456,
            "Null Count": 0,
            "Unique Values": 2,
            "Mean": 0.024012567324955117,
            "Median": 0.0,
            "Std": 0.1531052727158177,
            "Min": 0.0,
            "Max": 1.0,
            "Top": null,
            "Freq": null
        },
        "patient_a bit tired": {
            "DataType": "int64",
            "Non-Null Count": 4456,
            "Null Count": 0,
            "Unique Values": 2,
            "Mean": 0.03254039497307002,
            "Median": 0.0,
            "Std": 0.1774502302801147,
            "Min": 0.0,
            "Max": 1.0,
            "Top": null,
            "Freq": null
        },
        "patient_significant drop in motivation": {
            "DataType": "int64",
            "Non-Null Count": 4456,
            "Null Count": 0,
            "Unique Values": 2,
            "Mean": 0.01526032315978456,
            "Median": 0.0,
            "Std": 0.12260024005221504,
            "Min": 0.0,
            "Max": 1.0,
            "Top": null,
            "Freq": null
        },
        "patient_hopeless": {
            "DataType": "int64",
            "Non-Null Count": 4456,
            "Null Count": 0,
            "Unique Values": 2,
            "Mean": 0.03702872531418312,
            "Median": 0.0,
            "Std": 0.18885338960723308,
            "Min": 0.0,
            "Max": 1.0,
            "Top": null,
            "Freq": null
        },
        "patient_loss of interest in hobbies": {
            "DataType": "int64",
            "Non-Null Count": 4456,
            "Null Count": 0,
            "Unique Values": 2,
            "Mean": 0.04129263913824058,
            "Median": 0.0,
            "Std": 0.1989885503919948,
            "Min": 0.0,
            "Max": 1.0,
            "Top": null,
            "Freq": null
        },
        "patient_difficulty functioning": {
            "DataType": "int64",
            "Non-Null Count": 4456,
            "Null Count": 0,
            "Unique Values": 2,
            "Mean": 0.019299820466786355,
            "Median": 0.0,
            "Std": 0.13759209990882126,
            "Min": 0.0,
            "Max": 1.0,
            "Top": null,
            "Freq": null
        },
        "patient_sometimes feeling distracted": {
            "DataType": "int64",
            "Non-Null Count": 4456,
            "Null Count": 0,
            "Unique Values": 2,
            "Mean": 0.03141831238779174,
            "Median": 0.0,
            "Std": 0.174464990275439,
            "Min": 0.0,
            "Max": 1.0,
            "Top": null,
            "Freq": null
        },
        "patient_completely drained": {
            "DataType": "int64",
            "Non-Null Count": 4456,
            "Null Count": 0,
            "Unique Values": 2,
            "Mean": 0.012342908438061042,
            "Median": 0.0,
            "Std": 0.11042326487969194,
            "Min": 0.0,
            "Max": 1.0,
            "Top": null,
            "Freq": null
        },
        "patient_motivation is extremely low": {
            "DataType": "int64",
            "Non-Null Count": 4456,
            "Null Count": 0,
            "Unique Values": 2,
            "Mean": 0.1059245960502693,
            "Median": 0.0,
            "Std": 0.30777562288720633,
            "Min": 0.0,
            "Max": 1.0,
            "Top": null,
            "Freq": null
        },
        "patient_thoughts of self-harm": {
            "DataType": "int64",
            "Non-Null Count": 4456,
            "Null Count": 0,
            "Unique Values": 2,
            "Mean": 0.012567324955116697,
            "Median": 0.0,
            "Std": 0.11140993131304311,
            "Min": 0.0,
            "Max": 1.0,
            "Top": null,
            "Freq": null
        },
        "patient_persistent guilt and self-criticism": {
            "DataType": "int64",
            "Non-Null Count": 4456,
            "Null Count": 0,
            "Unique Values": 2,
            "Mean": 0.0062836624775583485,
            "Median": 0.0,
            "Std": 0.07902897996725035,
            "Min": 0.0,
            "Max": 1.0,
            "Top": null,
            "Freq": null
        },
        "patient_worthless": {
            "DataType": "int64",
            "Non-Null Count": 4456,
            "Null Count": 0,
            "Unique Values": 2,
            "Mean": 0.020197486535008975,
            "Median": 0.0,
            "Std": 0.14069111617657287,
            "Min": 0.0,
            "Max": 1.0,
            "Top": null,
            "Freq": null
        },
        "patient_minor irritability": {
            "DataType": "int64",
            "Non-Null Count": 4456,
            "Null Count": 0,
            "Unique Values": 2,
            "Mean": 0.048922800718132854,
            "Median": 0.0,
            "Std": 0.21573086146603365,
            "Min": 0.0,
            "Max": 1.0,
            "Top": null,
            "Freq": null
        },
        "patient_inability to get out of bed": {
            "DataType": "int64",
            "Non-Null Count": 4456,
            "Null Count": 0,
            "Unique Values": 2,
            "Mean": 0.004263913824057451,
            "Median": 0.0,
            "Std": 0.06516660102701992,
            "Min": 0.0,
            "Max": 1.0,
            "Top": null,
            "Freq": null
        },
        "patient_discouraged": {
            "DataType": "int64",
            "Non-Null Count": 4456,
            "Null Count": 0,
            "Unique Values": 2,
            "Mean": 0.029398563734290842,
            "Median": 0.0,
            "Std": 0.16893990999053837,
            "Min": 0.0,
            "Max": 1.0,
            "Top": null,
            "Freq": null
        },
        "patient_exhausted": {
            "DataType": "int64",
            "Non-Null Count": 4456,
            "Null Count": 0,
            "Unique Values": 2,
            "Mean": 0.025583482944344704,
            "Median": 0.0,
            "Std": 0.15790682085585994,
            "Min": 0.0,
            "Max": 1.0,
            "Top": null,
            "Freq": null
        },
        "patient_helpless": {
            "DataType": "int64",
            "Non-Null Count": 4456,
            "Null Count": 0,
            "Unique Values": 2,
            "Mean": 0.009425493716337522,
            "Median": 0.0,
            "Std": 0.09663720584841747,
            "Min": 0.0,
            "Max": 1.0,
            "Top": null,
            "Freq": null
        },
        "patient_distraught": {
            "DataType": "int64",
            "Non-Null Count": 4456,
            "Null Count": 0,
            "Unique Values": 2,
            "Mean": 0.02917414721723519,
            "Median": 0.0,
            "Std": 0.1683133207170787,
            "Min": 0.0,
            "Max": 1.0,
            "Top": null,
            "Freq": null
        },
        "patient_bored": {
            "DataType": "int64",
            "Non-Null Count": 4456,
            "Null Count": 0,
            "Unique Values": 2,
            "Mean": 0.04196588868940754,
            "Median": 0.0,
            "Std": 0.20053373160593868,
            "Min": 0.0,
            "Max": 1.0,
            "Top": null,
            "Freq": null
        },
        "patient_frequent negative thoughts": {
            "DataType": "int64",
            "Non-Null Count": 4456,
            "Null Count": 0,
            "Unique Values": 2,
            "Mean": 0.05026929982046679,
            "Median": 0.0,
            "Std": 0.21852462991864535,
            "Min": 0.0,
            "Max": 1.0,
            "Top": null,
            "Freq": null
        },
        "patient_hopelessness": {
            "DataType": "int64",
            "Non-Null Count": 4456,
            "Null Count": 0,
            "Unique Values": 2,
            "Mean": 0.017055655296229804,
            "Median": 0.0,
            "Std": 0.1294933320761557,
            "Min": 0.0,
            "Max": 1.0,
            "Top": null,
            "Freq": null
        },
        "patient_intense fear of future": {
            "DataType": "int64",
            "Non-Null Count": 4456,
            "Null Count": 0,
            "Unique Values": 2,
            "Mean": 0.004039497307001795,
            "Median": 0.0,
            "Std": 0.06343565905043967,
            "Min": 0.0,
            "Max": 1.0,
            "Top": null,
            "Freq": null
        },
        "patient_social withdrawal": {
            "DataType": "int64",
            "Non-Null Count": 4456,
            "Null Count": 0,
            "Unique Values": 2,
            "Mean": 0.027827648114901255,
            "Median": 0.0,
            "Std": 0.164497242161479,
            "Min": 0.0,
            "Max": 1.0,
            "Top": null,
            "Freq": null
        },
        "patient_anxious": {
            "DataType": "int64",
            "Non-Null Count": 4456,
            "Null Count": 0,
            "Unique Values": 2,
            "Mean": 0.048025134649910234,
            "Median": 0.0,
            "Std": 0.21384336190529343,
            "Min": 0.0,
            "Max": 1.0,
            "Top": null,
            "Freq": null
        },
        "patient_difficulty enjoying usual activities": {
            "DataType": "int64",
            "Non-Null Count": 4456,
            "Null Count": 0,
            "Unique Values": 2,
            "Mean": 0.05565529622980251,
            "Median": 0.0,
            "Std": 0.22928057421815468,
            "Min": 0.0,
            "Max": 1.0,
            "Top": null,
            "Freq": null
        },
        "patient_slightly low": {
            "DataType": "int64",
            "Non-Null Count": 4456,
            "Null Count": 0,
            "Unique Values": 2,
            "Mean": 0.03433572710951526,
            "Median": 0.0,
            "Std": 0.18211048172418476,
            "Min": 0.0,
            "Max": 1.0,
            "Top": null,
            "Freq": null
        },
        "doctor_evaluation": {
            "DataType": "int64",
            "Non-Null Count": 4456,
            "Null Count": 0,
            "Unique Values": 2,
            "Mean": 0.03949730700179533,
            "Median": 0.0,
            "Std": 0.19479677975366588,
            "Min": 0.0,
            "Max": 1.0,
            "Top": null,
            "Freq": null
        },
        "doctor_Moderate": {
            "DataType": "int64",
            "Non-Null Count": 4456,
            "Null Count": 0,
            "Unique Values": 2,
            "Mean": 0.4115798922800718,
            "Median": 0.0,
            "Std": 0.4921750159907656,
            "Min": 0.0,
            "Max": 1.0,
            "Top": null,
            "Freq": null
        },
        "doctor_visit": {
            "DataType": "int64",
            "Non-Null Count": 4456,
            "Null Count": 0,
            "Unique Values": 2,
            "Mean": 0.12365350089766607,
            "Median": 0.0,
            "Std": 0.3292227765348446,
            "Min": 0.0,
            "Max": 1.0,
            "Top": null,
            "Freq": null
        },
        "doctor_behavioral": {
            "DataType": "int64",
            "Non-Null Count": 4456,
            "Null Count": 0,
            "Unique Values": 2,
            "Mean": 0.12365350089766607,
            "Median": 0.0,
            "Std": 0.3292227765348446,
            "Min": 0.0,
            "Max": 1.0,
            "Top": null,
            "Freq": null
        },
        "doctor_safety": {
            "DataType": "int64",
            "Non-Null Count": 4456,
            "Null Count": 0,
            "Unique Values": 2,
            "Mean": 0.03949730700179533,
            "Median": 0.0,
            "Std": 0.19479677975366588,
            "Min": 0.0,
            "Max": 1.0,
            "Top": null,
            "Freq": null
        },
        "doctor_monitoring": {
            "DataType": "int64",
            "Non-Null Count": 4456,
            "Null Count": 0,
            "Unique Values": 2,
            "Mean": 0.2585278276481149,
            "Median": 0.0,
            "Std": 0.4378746604967384,
            "Min": 0.0,
            "Max": 1.0,
            "Top": null,
            "Freq": null
        },
        "doctor_review": {
            "DataType": "int64",
            "Non-Null Count": 4456,
            "Null Count": 0,
            "Unique Values": 2,
            "Mean": 0.12365350089766607,
            "Median": 0.0,
            "Std": 0.3292227765348446,
            "Min": 0.0,
            "Max": 1.0,
            "Top": null,
            "Freq": null
        },
        "doctor_Severe": {
            "DataType": "int64",
            "Non-Null Count": 4456,
            "Null Count": 0,
            "Unique Values": 2,
            "Mean": 0.2268850987432675,
            "Median": 0.0,
            "Std": 0.41886468466109866,
            "Min": 0.0,
            "Max": 1.0,
            "Top": null,
            "Freq": null
        },
        "doctor_Mild": {
            "DataType": "int64",
            "Non-Null Count": 4456,
            "Null Count": 0,
            "Unique Values": 2,
            "Mean": 0.35412926391382404,
            "Median": 0.0,
            "Std": 0.47830227765397004,
            "Min": 0.0,
            "Max": 1.0,
            "Top": null,
            "Freq": null
        },
        "doctor_progress": {
            "DataType": "int64",
            "Non-Null Count": 4456,
            "Null Count": 0,
            "Unique Values": 2,
            "Mean": 0.12365350089766607,
            "Median": 0.0,
            "Std": 0.3292227765348446,
            "Min": 0.0,
            "Max": 1.0,
            "Top": null,
            "Freq": null
        },
        "doctor_maintaining": {
            "DataType": "int64",
            "Non-Null Count": 4456,
            "Null Count": 0,
            "Unique Values": 2,
            "Mean": 0.07697486535008977,
            "Median": 0.0,
            "Std": 0.26658147679022753,
            "Min": 0.0,
            "Max": 1.0,
            "Top": null,
            "Freq": null
        },
        "doctor_structured": {
            "DataType": "int64",
            "Non-Null Count": 4456,
            "Null Count": 0,
            "Unique Values": 2,
            "Mean": 0.13487432675044883,
            "Median": 0.0,
            "Std": 0.34162762514001394,
            "Min": 0.0,
            "Max": 1.0,
            "Top": null,
            "Freq": null
        },
        "doctor_risk": {
            "DataType": "int64",
            "Non-Null Count": 4456,
            "Null Count": 0,
            "Unique Values": 2,
            "Mean": 0.11220825852782765,
            "Median": 0.0,
            "Std": 0.31565792575373885,
            "Min": 0.0,
            "Max": 1.0,
            "Top": null,
            "Freq": null
        },
        "doctor_mindfulness": {
            "DataType": "int64",
            "Non-Null Count": 4456,
            "Null Count": 0,
            "Unique Values": 2,
            "Mean": 0.17504488330341114,
            "Median": 0.0,
            "Std": 0.38004813654100666,
            "Min": 0.0,
            "Max": 1.0,
            "Top": null,
            "Freq": null
        },
        "doctor_possible": {
            "DataType": "int64",
            "Non-Null Count": 4456,
            "Null Count": 0,
            "Unique Values": 2,
            "Mean": 0.07517953321364453,
            "Median": 0.0,
            "Std": 0.2637104048708229,
            "Min": 0.0,
            "Max": 1.0,
            "Top": null,
            "Freq": null
        },
        "doctor_care": {
            "DataType": "int64",
            "Non-Null Count": 4456,
            "Null Count": 0,
            "Unique Values": 2,
            "Mean": 0.11131059245960502,
            "Median": 0.0,
            "Std": 0.31455166324942907,
            "Min": 0.0,
            "Max": 1.0,
            "Top": null,
            "Freq": null
        },
        "doctor_medication": {
            "DataType": "int64",
            "Non-Null Count": 4456,
            "Null Count": 0,
            "Unique Values": 2,
            "Mean": 0.07517953321364453,
            "Median": 0.0,
            "Std": 0.2637104048708229,
            "Min": 0.0,
            "Max": 1.0,
            "Top": null,
            "Freq": null
        },
        "doctor_planning": {
            "DataType": "int64",
            "Non-Null Count": 4456,
            "Null Count": 0,
            "Unique Values": 2,
            "Mean": 0.03949730700179533,
            "Median": 0.0,
            "Std": 0.19479677975366588,
            "Min": 0.0,
            "Max": 1.0,
            "Top": null,
            "Freq": null
        },
        "doctor_urgent": {
            "DataType": "int64",
            "Non-Null Count": 4456,
            "Null Count": 0,
            "Unique Values": 2,
            "Mean": 0.03949730700179533,
            "Median": 0.0,
            "Std": 0.19479677975366588,
            "Min": 0.0,
            "Max": 1.0,
            "Top": null,
            "Freq": null
        },
        "doctor_intervention": {
            "DataType": "int64",
            "Non-Null Count": 4456,
            "Null Count": 0,
            "Unique Values": 2,
            "Mean": 0.11781867145421904,
            "Median": 0.0,
            "Std": 0.32242946922271265,
            "Min": 0.0,
            "Max": 1.0,
            "Top": null,
            "Freq": null
        },
        "doctor_recommended": {
            "DataType": "int64",
            "Non-Null Count": 4456,
            "Null Count": 0,
            "Unique Values": 2,
            "Mean": 0.03433572710951526,
            "Median": 0.0,
            "Std": 0.18211048172418476,
            "Min": 0.0,
            "Max": 1.0,
            "Top": null,
            "Freq": null
        },
        "doctor_active": {
            "DataType": "int64",
            "Non-Null Count": 4456,
            "Null Count": 0,
            "Unique Values": 2,
            "Mean": 0.08348294434470377,
            "Median": 0.0,
            "Std": 0.27664185710991634,
            "Min": 0.0,
            "Max": 1.0,
            "Top": null,
            "Freq": null
        },
        "doctor_symptoms": {
            "DataType": "int64",
            "Non-Null Count": 4456,
            "Null Count": 0,
            "Unique Values": 2,
            "Mean": 0.3720825852782765,
            "Median": 0.0,
            "Std": 0.4834145000020788,
            "Min": 0.0,
            "Max": 1.0,
            "Top": null,
            "Freq": null
        },
        "doctor_advised": {
            "DataType": "int64",
            "Non-Null Count": 4456,
            "Null Count": 0,
            "Unique Values": 2,
            "Mean": 0.12365350089766607,
            "Median": 0.0,
            "Std": 0.3292227765348446,
            "Min": 0.0,
            "Max": 1.0,
            "Top": null,
            "Freq": null
        },
        "doctor_specialist": {
            "DataType": "int64",
            "Non-Null Count": 4456,
            "Null Count": 0,
            "Unique Values": 2,
            "Mean": 0.0778725314183124,
            "Median": 0.0,
            "Std": 0.2680009680526956,
            "Min": 0.0,
            "Max": 1.0,
            "Top": null,
            "Freq": null
        },
        "doctor_immediate": {
            "DataType": "int64",
            "Non-Null Count": 4456,
            "Null Count": 0,
            "Unique Values": 2,
            "Mean": 0.03433572710951526,
            "Median": 0.0,
            "Std": 0.18211048172418476,
            "Min": 0.0,
            "Max": 1.0,
            "Top": null,
            "Freq": null
        },
        "doctor_referral": {
            "DataType": "int64",
            "Non-Null Count": 4456,
            "Null Count": 0,
            "Unique Values": 2,
            "Mean": 0.15305206463195692,
            "Median": 0.0,
            "Std": 0.36007808478545617,
            "Min": 0.0,
            "Max": 1.0,
            "Top": null,
            "Freq": null
        },
        "doctor_routines": {
            "DataType": "int64",
            "Non-Null Count": 4456,
            "Null Count": 0,
            "Unique Values": 2,
            "Mean": 0.07697486535008977,
            "Median": 0.0,
            "Std": 0.26658147679022753,
            "Min": 0.0,
            "Max": 1.0,
            "Top": null,
            "Freq": null
        },
        "doctor_healthy": {
            "DataType": "int64",
            "Non-Null Count": 4456,
            "Null Count": 0,
            "Unique Values": 2,
            "Mean": 0.07697486535008977,
            "Median": 0.0,
            "Std": 0.26658147679022753,
            "Min": 0.0,
            "Max": 1.0,
            "Top": null,
            "Freq": null
        },
        "doctor_factors": {
            "DataType": "int64",
            "Non-Null Count": 4456,
            "Null Count": 0,
            "Unique Values": 2,
            "Mean": 0.0778725314183124,
            "Median": 0.0,
            "Std": 0.2680009680526956,
            "Min": 0.0,
            "Max": 1.0,
            "Top": null,
            "Freq": null
        },
        "doctor_guided": {
            "DataType": "int64",
            "Non-Null Count": 4456,
            "Null Count": 0,
            "Unique Values": 2,
            "Mean": 0.17908438061041293,
            "Median": 0.0,
            "Std": 0.3834659891306567,
            "Min": 0.0,
            "Max": 1.0,
            "Top": null,
            "Freq": null
        },
        "doctor_next": {
            "DataType": "int64",
            "Non-Null Count": 4456,
            "Null Count": 0,
            "Unique Values": 2,
            "Mean": 0.12365350089766607,
            "Median": 0.0,
            "Std": 0.3292227765348446,
            "Min": 0.0,
            "Max": 1.0,
            "Top": null,
            "Freq": null
        },
        "doctor_exercises": {
            "DataType": "int64",
            "Non-Null Count": 4456,
            "Null Count": 0,
            "Unique Values": 2,
            "Mean": 0.17504488330341114,
            "Median": 0.0,
            "Std": 0.38004813654100666,
            "Min": 0.0,
            "Max": 1.0,
            "Top": null,
            "Freq": null
        },
        "doctor_combination": {
            "DataType": "int64",
            "Non-Null Count": 4456,
            "Null Count": 0,
            "Unique Values": 2,
            "Mean": 0.07517953321364453,
            "Median": 0.0,
            "Std": 0.2637104048708229,
            "Min": 0.0,
            "Max": 1.0,
            "Top": null,
            "Freq": null
        },
        "doctor_selfhelp": {
            "DataType": "int64",
            "Non-Null Count": 4456,
            "Null Count": 0,
            "Unique Values": 1,
            "Mean": 0.0,
            "Median": 0.0,
            "Std": 0.0,
            "Min": 0.0,
            "Max": 0.0,
            "Top": null,
            "Freq": null
        },
        "doctor_escalates": {
            "DataType": "int64",
            "Non-Null Count": 4456,
            "Null Count": 0,
            "Unique Values": 2,
            "Mean": 0.03433572710951526,
            "Median": 0.0,
            "Std": 0.18211048172418476,
            "Min": 0.0,
            "Max": 1.0,
            "Top": null,
            "Freq": null
        },
        "doctor_psychiatric": {
            "DataType": "int64",
            "Non-Null Count": 4456,
            "Null Count": 0,
            "Unique Values": 2,
            "Mean": 0.03949730700179533,
            "Median": 0.0,
            "Std": 0.19479677975366588,
            "Min": 0.0,
            "Max": 1.0,
            "Top": null,
            "Freq": null
        },
        "doctor_needed": {
            "DataType": "int64",
            "Non-Null Count": 4456,
            "Null Count": 0,
            "Unique Values": 2,
            "Mean": 0.08348294434470377,
            "Median": 0.0,
            "Std": 0.27664185710991634,
            "Min": 0.0,
            "Max": 1.0,
            "Top": null,
            "Freq": null
        },
        "doctor_required": {
            "DataType": "int64",
            "Non-Null Count": 4456,
            "Null Count": 0,
            "Unique Values": 2,
            "Mean": 0.03949730700179533,
            "Median": 0.0,
            "Std": 0.19479677975366588,
            "Min": 0.0,
            "Max": 1.0,
            "Top": null,
            "Freq": null
        },
        "doctor_and": {
            "DataType": "int64",
            "Non-Null Count": 4456,
            "Null Count": 0,
            "Unique Values": 2,
            "Mean": 0.36669658886894074,
            "Median": 0.0,
            "Std": 0.481956770438984,
            "Min": 0.0,
            "Max": 1.0,
            "Top": null,
            "Freq": null
        },
        "doctor_consider": {
            "DataType": "int64",
            "Non-Null Count": 4456,
            "Null Count": 0,
            "Unique Values": 2,
            "Mean": 0.2134201077199282,
            "Median": 0.0,
            "Std": 0.4097677964883416,
            "Min": 0.0,
            "Max": 1.0,
            "Top": null,
            "Freq": null
        },
        "doctor_cognitive": {
            "DataType": "int64",
            "Non-Null Count": 4456,
            "Null Count": 0,
            "Unique Values": 2,
            "Mean": 0.12365350089766607,
            "Median": 0.0,
            "Std": 0.3292227765348446,
            "Min": 0.0,
            "Max": 1.0,
            "Top": null,
            "Freq": null
        },
        "doctor_inpatient": {
            "DataType": "int64",
            "Non-Null Count": 4456,
            "Null Count": 0,
            "Unique Values": 2,
            "Mean": 0.03433572710951526,
            "Median": 0.0,
            "Std": 0.18211048172418476,
            "Min": 0.0,
            "Max": 1.0,
            "Top": null,
            "Freq": null
        },
        "doctor_encourage": {
            "DataType": "int64",
            "Non-Null Count": 4456,
            "Null Count": 0,
            "Unique Values": 2,
            "Mean": 0.07697486535008977,
            "Median": 0.0,
            "Std": 0.26658147679022753,
            "Min": 0.0,
            "Max": 1.0,
            "Top": null,
            "Freq": null
        },
        "doctor_continue": {
            "DataType": "int64",
            "Non-Null Count": 4456,
            "Null Count": 0,
            "Unique Values": 2,
            "Mean": 0.2910682226211849,
            "Median": 0.0,
            "Std": 0.45430587778052267,
            "Min": 0.0,
            "Max": 1.0,
            "Top": null,
            "Freq": null
        },
        "doctor_suggest": {
            "DataType": "int64",
            "Non-Null Count": 4456,
            "Null Count": 0,
            "Unique Values": 2,
            "Mean": 0.0778725314183124,
            "Median": 0.0,
            "Std": 0.2680009680526956,
            "Min": 0.0,
            "Max": 1.0,
            "Top": null,
            "Freq": null
        },
        "doctor_lowintensity": {
            "DataType": "int64",
            "Non-Null Count": 4456,
            "Null Count": 0,
            "Unique Values": 1,
            "Mean": 0.0,
            "Median": 0.0,
            "Std": 0.0,
            "Min": 0.0,
            "Max": 0.0,
            "Top": null,
            "Freq": null
        },
        "doctor_therapy": {
            "DataType": "int64",
            "Non-Null Count": 4456,
            "Null Count": 0,
            "Unique Values": 2,
            "Mean": 0.33370736086175945,
            "Median": 0.0,
            "Std": 0.4715895118150939,
            "Min": 0.0,
            "Max": 1.0,
            "Top": null,
            "Freq": null
        },
        "doctor_monitor": {
            "DataType": "int64",
            "Non-Null Count": 4456,
            "Null Count": 0,
            "Unique Values": 2,
            "Mean": 0.47127468581687615,
            "Median": 0.0,
            "Std": 0.4992301952310464,
            "Min": 0.0,
            "Max": 1.0,
            "Top": null,
            "Freq": null
        },
        "doctor_selfcare": {
            "DataType": "int64",
            "Non-Null Count": 4456,
            "Null Count": 0,
            "Unique Values": 1,
            "Mean": 0.0,
            "Median": 0.0,
            "Std": 0.0,
            "Min": 0.0,
            "Max": 0.0,
            "Top": null,
            "Freq": null
        },
        "doctor_None-minimal": {
            "DataType": "int64",
            "Non-Null Count": 4456,
            "Null Count": 0,
            "Unique Values": 2,
            "Mean": 0.16045780969479354,
            "Median": 0.0,
            "Std": 0.36707129986527987,
            "Min": 0.0,
            "Max": 1.0,
            "Top": null,
            "Freq": null
        },
        "doctor_mental": {
            "DataType": "int64",
            "Non-Null Count": 4456,
            "Null Count": 0,
            "Unique Values": 2,
            "Mean": 0.0778725314183124,
            "Median": 0.0,
            "Std": 0.2680009680526956,
            "Min": 0.0,
            "Max": 1.0,
            "Top": null,
            "Freq": null
        },
        "doctor_recommend": {
            "DataType": "int64",
            "Non-Null Count": 4456,
            "Null Count": 0,
            "Unique Values": 2,
            "Mean": 0.34425493716337524,
            "Median": 0.0,
            "Std": 0.4751780164718618,
            "Min": 0.0,
            "Max": 1.0,
            "Top": null,
            "Freq": null
        },
        "doctor_health": {
            "DataType": "int64",
            "Non-Null Count": 4456,
            "Null Count": 0,
            "Unique Values": 2,
            "Mean": 0.15484739676840215,
            "Median": 0.0,
            "Std": 0.3617997462585798,
            "Min": 0.0,
            "Max": 1.0,
            "Top": null,
            "Freq": null
        },
        "doctor_closely": {
            "DataType": "int64",
            "Non-Null Count": 4456,
            "Null Count": 0,
            "Unique Values": 2,
            "Mean": 0.13487432675044883,
            "Median": 0.0,
            "Std": 0.34162762514001394,
            "Min": 0.0,
            "Max": 1.0,
            "Top": null,
            "Freq": null
        },
        "doctor_Moderately Severe": {
            "DataType": "int64",
            "Non-Null Count": 4456,
            "Null Count": 0,
            "Unique Values": 2,
            "Mean": 0.15305206463195692,
            "Median": 0.0,
            "Std": 0.36007808478545617,
            "Min": 0.0,
            "Max": 1.0,
            "Top": null,
            "Freq": null
        },
        "doctor_cbt": {
            "DataType": "int64",
            "Non-Null Count": 4456,
            "Null Count": 0,
            "Unique Values": 2,
            "Mean": 0.302737881508079,
            "Median": 0.0,
            "Std": 0.45949432945153396,
            "Min": 0.0,
            "Max": 1.0,
            "Top": null,
            "Freq": null
        },
        "patient_suicide_score": {
            "DataType": "int64",
            "Non-Null Count": 4456,
            "Null Count": 0,
            "Unique Values": 3,
            "Mean": 0.09111310592459605,
            "Median": 0.0,
            "Std": 0.360510947729933,
            "Min": 0.0,
            "Max": 2.0,
            "Top": null,
            "Freq": null
        },
        "doctor_suicide_score": {
            "DataType": "int64",
            "Non-Null Count": 4456,
            "Null Count": 0,
            "Unique Values": 3,
            "Mean": 0.09111310592459605,
            "Median": 0.0,
            "Std": 0.360510947729933,
            "Min": 0.0,
            "Max": 2.0,
            "Top": null,
            "Freq": null
        },
        "patient_anxiety_score": {
            "DataType": "int64",
            "Non-Null Count": 4456,
            "Null Count": 0,
            "Unique Values": 4,
            "Mean": 0.2885996409335727,
            "Median": 0.0,
            "Std": 0.6511426306294122,
            "Min": 0.0,
            "Max": 3.0,
            "Top": null,
            "Freq": null
        },
        "doctor_anxiety_score": {
            "DataType": "int64",
            "Non-Null Count": 4456,
            "Null Count": 0,
            "Unique Values": 4,
            "Mean": 0.2885996409335727,
            "Median": 0.0,
            "Std": 0.6511426306294122,
            "Min": 0.0,
            "Max": 3.0,
            "Top": null,
            "Freq": null
        },
        "patient_symptom_score": {
            "DataType": "int64",
            "Non-Null Count": 4456,
            "Null Count": 0,
            "Unique Values": 3,
            "Mean": 2.971274685816876,
            "Median": 3.0,
            "Std": 0.6082713007041207,
            "Min": 2.0,
            "Max": 4.0,
            "Top": null,
            "Freq": null
        },
        "doctor_symptom_score": {
            "DataType": "int64",
            "Non-Null Count": 4456,
            "Null Count": 0,
            "Unique Values": 3,
            "Mean": 2.971274685816876,
            "Median": 3.0,
            "Std": 0.6082713007041207,
            "Min": 2.0,
            "Max": 4.0,
            "Top": null,
            "Freq": null
        },
        "consultation_seq": {
            "DataType": "int64",
            "Non-Null Count": 4456,
            "Null Count": 0,
            "Unique Values": 64,
            "Mean": 19.453770197486534,
            "Median": 17.0,
            "Std": 13.73875605290325,
            "Min": 1.0,
            "Max": 64.0,
            "Top": null,
            "Freq": null
        },
        "days_since_last": {
            "DataType": "float64",
            "Non-Null Count": 4456,
            "Null Count": 0,
            "Unique Values": 117,
            "Mean": 11.646992818671455,
            "Median": 7.0,
            "Std": 16.906129688175056,
            "Min": 0.0,
            "Max": 208.0,
            "Top": null,
            "Freq": null
        }
    }
}